CHANGELOG.rst
LICENSE
MANIFEST.in
README.rst
setup.cfg
setup.py
adminextraviews/__init__.py
adminextraviews/models.py
adminextraviews/tests.py
django_adminextraviews.egg-info/PKG-INFO
django_adminextraviews.egg-info/SOURCES.txt
django_adminextraviews.egg-info/dependency_links.txt
django_adminextraviews.egg-info/requires.txt
django_adminextraviews.egg-info/top_level.txt
django_adminextraviews.egg-info/zip-safe