Metadata-Version: 1.1
Name: django-adminextraviews
Version: 1.1.0
Summary: Mixin for adding class-based views to ModelAdmin
Home-page: https://github.com/fusionbox/django-adminextraviews
Author: Fusionbox, Inc.
Author-email: programmers@fusionbox.com
License: Apache 2.0
Keywords: django-adminextraviews
Platform: UNKNOWN
Classifier: Development Status :: 5 - Production/Stable
Classifier: Framework :: Django
Classifier: Intended Audience :: Developers
Classifier: License :: OSI Approved :: Apache Software License
Classifier: Natural Language :: English
Classifier: Programming Language :: Python :: 2
Classifier: Programming Language :: Python :: 2.6
Classifier: Programming Language :: Python :: 2.7
Classifier: Programming Language :: Python :: 3
Classifier: Programming Language :: Python :: 3.3
Classifier: Programming Language :: Python :: 3.4
